sqlcrafty/__init__.py
sqlcrafty/functions.py
sqlcrafty/models.py
sqlcrafty/sqlcrafty.py
sqlcrafty/utils.py
sqlcrafty-0.0.0.dist-info/METADATA
sqlcrafty-0.0.0.dist-info/WHEEL
sqlcrafty-0.0.0.dist-info/entry_points.txt
sqlcrafty-0.0.0.dist-info/top_level.txt
sqlcrafty-0.0.0.dist-info/RECORD
